pygbm/__init__.py
pygbm/base_pygbm.py
pygbm/cli.py
pygbm/version.py
pygbm/gbm_simulator/__init__.py
pygbm/gbm_simulator/gbm_simulator.py
pygbm_hej-0.1.0.post2.dist-info/licenses/LICENSE
pygbm_hej-0.1.0.post2.dist-info/METADATA
pygbm_hej-0.1.0.post2.dist-info/WHEEL
pygbm_hej-0.1.0.post2.dist-info/entry_points.txt
pygbm_hej-0.1.0.post2.dist-info/top_level.txt
pygbm_hej-0.1.0.post2.dist-info/RECORD
