Metadata-Version: 2.4
Name: pygbm_hej
Version: 0.1.0.post2
Summary: A Python package for simulating Geometric Brownian Motion.
Author-email: Randa He <jh2604@cam.ac.uk>
License: MIT License
Project-URL: Documentation, https://your-readthedocs-url-here
Project-URL: Source, https://github.com/randa1029/pygbm.git
Project-URL: Issues, https://github.com/randa1029/pygbm.git/issues
Keywords: Geometric Brownian Motion,simulation
Classifier: Development Status :: 4 - Beta
Classifier: Intended Audience :: Science/Research
Classifier: License :: OSI Approved :: MIT License
Classifier: Programming Language :: Python :: 3
Classifier: Topic :: Software Development :: Libraries
Requires-Python: >=3.9
License-File: LICENSE
Requires-Dist: numpy
Requires-Dist: pandas
Requires-Dist: argparse
Requires-Dist: datetime
Requires-Dist: importlib.resources
Dynamic: license-file
